zmqrpc/__init__.py
zmqrpc/base/ZmqBase.py
zmqrpc/base/__init__.py
zmqrpc/client/ZmqRpcClient.py
zmqrpc/client/__init__.py
zmqrpc/command/CommandDatabase.py
zmqrpc/command/CommandMeta.py
zmqrpc/command/ICommand.py
zmqrpc/command/JsonEncoder.py
zmqrpc/command/ShutdownServer.py
zmqrpc/command/__init__.py
zmqrpc/command/json_io.py
zmqrpc/logger/__init__.py
zmqrpc/proxy/ZmqBufferedProxyRep2ReqThread.py
zmqrpc/proxy/ZmqProxy.py
zmqrpc/proxy/ZmqProxyRep2Pub.py
zmqrpc/proxy/ZmqProxyRep2PubThread.py
zmqrpc/proxy/ZmqProxyRep2Req.py
zmqrpc/proxy/ZmqProxyRep2ReqThread.py
zmqrpc/proxy/ZmqProxySub2Pub.py
zmqrpc/proxy/ZmqProxySub2PubThread.py
zmqrpc/proxy/ZmqProxySub2Req.py
zmqrpc/proxy/ZmqProxySub2ReqThread.py
zmqrpc/proxy/ZmqProxyThread.py
zmqrpc/proxy/__init__.py
zmqrpc/receiver/RepSocket.py
zmqrpc/receiver/SubSocket.py
zmqrpc/receiver/ZmqReceiver.py
zmqrpc/receiver/ZmqReceiverThread.py
zmqrpc/receiver/__init__.py
zmqrpc/sender/ZmqSender.py
zmqrpc/sender/__init__.py
zmqrpc/server/ZmqRpcServer.py
zmqrpc/server/ZmqRpcServerThread.py
zmqrpc/server/__init__.py
zmqrpc/service/IService.py
zmqrpc/service/ShutdownServerService.py
zmqrpc/service/__init__.py
pyzmqrpc3-3.2.2.dist-info/LICENSE.txt
pyzmqrpc3-3.2.2.dist-info/METADATA
pyzmqrpc3-3.2.2.dist-info/WHEEL
pyzmqrpc3-3.2.2.dist-info/top_level.txt
pyzmqrpc3-3.2.2.dist-info/RECORD
