Metadata-Version: 2.1
Name: pyzmqrpc3
Version: 3.2.2
Summary: A simple ZMQ RPC extension with command/service architecture
Home-page: https://github.com/brgirgis/pyzmqrpc3
Author: Bassem Girgis
Author-email: brgirgis@gmail.com
Maintainer: Bassem Girgis
Maintainer-email: brgirgis@gmail.com
License: MIT
Download-URL: https://pypi.org/project/pyzmqrpc3/
Keywords: zmq,zeromq,pyzmq,rpc
Platform: UNKNOWN
Classifier: Development Status :: 5 - Production/Stable
Classifier: Intended Audience :: Developers
Classifier: Topic :: Communications
Classifier: Topic :: Internet
Classifier: License :: OSI Approved :: MIT License
Classifier: Programming Language :: Python :: 3.6
Classifier: Programming Language :: Python :: 3.7
Classifier: Programming Language :: Python :: 3.8
Classifier: Programming Language :: Python :: 3.9
Requires-Dist: pyzmq (>=15.0.0)
Requires-Dist: future (>=0.15.0)
